pyversasense/__init__.py
pyversasense/const.py
pyversasense/consumer.py
pyversasense/device.py
pyversasense/peripheral.py
pyversasense-0.0.1.dist-info/LICENSE
pyversasense-0.0.1.dist-info/METADATA
pyversasense-0.0.1.dist-info/WHEEL
pyversasense-0.0.1.dist-info/top_level.txt
pyversasense-0.0.1.dist-info/zip-safe
pyversasense-0.0.1.dist-info/RECORD
