Metadata-Version: 2.1
Name: pyversasense
Version: 0.0.1
Summary: Versasense API consumer
Home-page: https://github.com/flamm3blemuff1n/pyversasense
Author: Steven Impens
Author-email: s.impens.dev@gmail.com
License: Apache License 2.0
Platform: UNKNOWN
Classifier: Programming Language :: Python :: 3
Classifier: Operating System :: OS Independent
Classifier: License :: OSI Approved :: Apache Software License
Requires-Dist: aiohttp (>=3.5.4)
